minimax_platform_video/__init__.py
minimax_platform_video/cache/__init__.py
minimax_platform_video/cache/json_pipeline_cache.py
minimax_platform_video/cache/pipeline_cache.py
minimax_platform_video/cache_data/VideoPullGenerator/VideoPullGenerator-84c05c6993416ccb12c39907278c2174
minimax_platform_video/cache_data/VideoStrategyGenerator/VideoStrategyGenerator-5f6bd139e50e6d47f52088689894193a
minimax_platform_video/cache_data/VideoStrategyPrompt/VideoStrategyPrompt-1614d56e3e28f49c20495ad6310ef96e
minimax_platform_video/download_video.py
minimax_platform_video/prompt_runner.py
minimax_platform_video/rate_limiter.py
minimax_platform_video/reporting/__init__.py
minimax_platform_video/reporting/console_workflow_callbacks.py
minimax_platform_video/reporting/runner_callbacks.py
minimax_platform_video/result_task.py
minimax_platform_video/start.py
minimax_platform_video/storage/__init__.py
minimax_platform_video/storage/_typing.py
minimax_platform_video/storage/file_pipeline_storage.py
minimax_platform_video/task.py
minimax_platform_video/utils.py
minimax_platform_video/video_pull.py
minimax_platform_video/video_pull_runner.py
minimax_platform_video/video_runner.py
minimax_platform_video-0.0.4.dist-info/METADATA
minimax_platform_video-0.0.4.dist-info/WHEEL
minimax_platform_video-0.0.4.dist-info/RECORD
